shcolor/__init__.py
shcolor/__main__.py
shcolor/linux.py
shcolor/utils.py
shcolor/win32.py
shcolor-0.0.2.dist-info/DESCRIPTION.rst
shcolor-0.0.2.dist-info/METADATA
shcolor-0.0.2.dist-info/RECORD
shcolor-0.0.2.dist-info/WHEEL
shcolor-0.0.2.dist-info/metadata.json
shcolor-0.0.2.dist-info/top_level.txt
